Workbook

Sheet README
A1: Canadian Restaurant Profitability Benchmark
A3: Question | B3: Where does a typical Canadian restaurant make and lose money, and how much would better labour, overhead and waste control change profit?
A4: Data | B4: Statistics Canada and ISED (Innovation, Science and Economic Development Canada) published restaurant financials, plus the Statistics Canada annual industry series for 2019 to 2024 and the hourly wage series for accommodation and food services. See the Sources tab.
A5: Benchmark tab | B5: The average Canadian restaurant (NAICS 7225, 65,071 businesses, 2024): revenue, each cost line as a share of revenue, profit quartiles, and the industry-wide cost structure from Statistics Canada.
A6: Scenario tab | B6: What-if on the average restaurant: apply a labour cut, an overhead cut and a waste cut (blue inputs) and see profit and margin. It also solves how small a cut produces +35% profit.
A7: Wages tab | B7: Average hourly wage in food services, 2020 to 2024, with yearly and cumulative growth.
A8: Industry_Trend tab | B8: Annual Statistics Canada figures for all food services and drinking places, 2019 to 2024: revenue, margin, cost shares, full-service vs limited-service, with charts.
A9: Colour code | B9: Blue text = input you can change. Black = formula. Every number on Benchmark, Wages and Industry_Trend is typed from the cited source; everything else is a formula.
A10: Limitations | B10: Averages hide wide differences between restaurants (the bottom quartile loses money). Scenario results are what-ifs on an average restaurant, not forecasts for a specific business. Waste share of food cost is an assumption you can edit.

Sheet Benchmark
A1: The average Canadian restaurant (2024)
A2: Source: ISED Canadian Industry Statistics, NAICS 7225 (Statistics Canada financial data), 65,071 businesses with revenue $30,000 to $5,000,000.
A4: Line | B4: Dollars per restaurant | C4: % of revenue | D4: Source
A5: Revenue | B5: 849200 | C5: =B5/$B$5 -> 1 | D5: ISED
A6: Cost of sales | B6: 380400 | C6: =B6/$B$5 -> 0.44795101 | D6: ISED
A7: Labour and commissions | B7: 200200 | C7: =B7/$B$5 -> 0.2357513 | D7: ISED
A8: Rent | B8: 71600 | C8: =B8/$B$5 -> 0.084314649 | D8: ISED
A9: Utilities and telecom | B9: 21500 | C9: =B9/$B$5 -> 0.025317946 | D9: ISED
A10: Amortization and depletion | B10: 23200 | C10: =B10/$B$5 -> 0.02731983 | D10: ISED
A11: Other expenses (calculated) | B11: =B5-B6-B7-B8-B9-B10-B12 -> 130800 | C11: =B11/$B$5 -> 0.15402732 | D11: Revenue less all listed costs and profit
A12: Net profit | B12: 21500 | C12: =B12/$B$5 -> 0.025317946 | D12: ISED
A13: Gross margin | B13: =B5-B6 -> 468800 | C13: =B13/$B$5 -> 0.55204899 | D13: Revenue less cost of sales (ISED reports 55.2%)
A15: Profit by quartile (average per restaurant)
A16: Group | B16: Profit ($) | C16: Margin on average revenue | D16: Note
A17: Bottom quartile | B17: -13000 | C17: =B17/$B$5 -> -0.015308526 | D17: Loses money
A18: Average | B18: =B12 -> 21500 | C18: =B18/$B$5 -> 0.025317946 | D18: 57.7% of restaurants are profitable, 42.3% lose money
A19: Top quartile | B19: 90600 | C19: =B19/$B$5 -> 0.10668865
A21: Industry-wide cost structure, Statistics Canada, 2024 (all food services and drinking places)
A22: Line | B22: Share of operating expenses or revenue | C22: 2023 comparison | D22: Note
A23: Operating revenue ($ billion) | B23: 99.6 | D23: +4.8% vs 2023
A24: Operating profit margin | B24: 0.041 | C24: 0.036 | D24: Improved from 3.6%
A25: Cost of goods sold | B25: 0.359 | D25: Share of operating expenses
A26: Salaries, wages, commissions and benefits | B26: 0.336 | D26: Share of operating expenses
A27: Rental and leasing | B27: 0.081 | D27: Share of operating expenses
A28: Limited-service revenue ($ billion) | B28: 44.9 | D28: +7.7%
A29: Full-service revenue ($ billion) | B29: 44.2 | D29: +1.4%
A31: Gap between the two sources: the ISED average restaurant has a 2.5% margin and 44.8% cost of sales, while the industry-wide 2024 figures are 4.1% and 35.9% of expenses (a different base). Compare lines within one source, not across.

Sheet Industry_Trend
A1: Canadian food services and drinking places, 2019 to 2024
A2: Source: Statistics Canada, The Daily annual releases (links on Sources). Blue = typed from the release. Blank = not published in the release I read. 2019 and 2022 values come from the later releases that compare to them (2022 was revised in 2024).
A4: Year | B4: Operating revenue ($B) | C4: Operating expenses ($B) | D4: Operating profit margin | E4: Full-service revenue ($B) | F4: Limited-service revenue ($B) | G4: Full-service margin | H4: Limited-service margin | I4: Cost of goods sold (% of expenses) | J4: Wages and benefits (% of expenses) | K4: Revenue vs 2019
A5: 2019 | B5: 78.4 | C5: 75.3 | D5: 0.038 | E5: 35.9 | F5: 33.4 | G5: 0.03 | H5: 0.039 | I5: 0.359 | J5: 0.332 | K5: =B5/$B$5-1 -> 0
A6: 2020 | B6: 58.4 | C6: 56.7 | D6: 0.029 | E6: 24.2 | F6: 28.9 | G6: 0.003 | H6: 0.053 | I6: 0.348 | J6: 0.323 | K6: =B6/$B$5-1 -> -0.25510204
A7: 2021 | B7: 67.5 | C7: 65 | D7: 0.037 | E7: 28.2 | F7: 33.6 | G7: 0.005 | H7: 0.069 | I7: 0.353 | J7: 0.32 | K7: =B7/$B$5-1 -> -0.13903061
A8: 2022 | B8: 84.2 | C8: 80.7 | D8: 0.043 | E8: 38.2 | F8: 37.7 | G8: 0.043 | H8: 0.04 | K8: =B8/$B$5-1 -> 0.073979592
A9: 2023 | B9: 95 | C9: 91.6 | D9: 0.036 | E9: 43.6 | F9: 41.7 | I9: 0.357 | J9: 0.334 | K9: =B9/$B$5-1 -> 0.21173469
A10: 2024 | B10: 99.6 | C10: 95.5 | D10: 0.041 | E10: 44.2 | F10: 44.9 | I10: 0.359 | J10: 0.336 | K10: =B10/$B$5-1 -> 0.27040816
A12: Revenue growth year over year
A13: 2020 | B13: =B6/B5-1 -> -0.25510204
A14: 2021 | B14: =B7/B6-1 -> 0.15582192
A15: 2022 | B15: =B8/B7-1 -> 0.24740741
A16: 2023 | B16: =B9/B8-1 -> 0.12826603
A17: 2024 | B17: =B10/B9-1 -> 0.048421053
A19: What the data says
A20: In 2020 full-service restaurants fell to a 0.3% margin while limited-service (take-out and counter) places earned 5.3%. Limited-service (counter and take-out style) places held up far better than full-service.
A21: Industry margins stay thin (3% to 4%) in every year, so small cost improvements matter.
A22: Cost of goods sold is about 35% to 36% and wages about 32% to 34% of expenses every year.
A23: Workforce (Statistics Canada, 2025): salaries, wages and commissions rose 22.2% from 2019 to 2023; job vacancy rate peaked at 13.4% in Q3 2021, then 10.2% in 2022 and 7.1% in 2023.

Sheet Scenario
A1: What-if: improving the average restaurant
A2: Blue cells are inputs. Base figures come from the Benchmark tab.
A4: Lever | B4: Input | C4: Dollar effect on profit | D4: How it is calculated
A5: Labour cost reduction | B5: 0.1 | C5: =Benchmark!B7*B5 -> 20020 | D5: Labour cost x cut
A6: Overhead reduction (utilities, telecom and other) | B6: 0.15 | C6: =(Benchmark!B9+Benchmark!B11)*B6 -> 22845 | D6: (Utilities + other expenses) x cut
A7: Food waste as share of cost of sales (assumption) | B7: 0.05 | D7: Assumption: edit. Not from the source data.
A8: Food waste reduction | B8: 0.2 | C8: =Benchmark!B6*B7*B8 -> 3804 | D8: Cost of sales x waste share x reduction
A10: Total profit improvement | C10: =C5+C6+C8 -> 46669
A11: Profit before | C11: =Benchmark!B12 -> 21500
A12: Profit after | C12: =C11+C10 -> 68169
A13: Profit change | C13: =C12/C11-1 -> 2.1706512
A14: Margin before | C14: =C11/Benchmark!B5 -> 0.025317946
A15: Margin after | C15: =C12/Benchmark!B5 -> 0.080274376
A17: How small a change gives +35% profit?
A18: Target profit growth | B18: 0.35
A19: Extra profit needed | C19: =Benchmark!B12*B18 -> 7525
A20: As % of revenue | C20: =C19/Benchmark!B5 -> 0.0088612812
A21: Equivalent labour cut alone | C21: =C19/Benchmark!B7 -> 0.037587413
A22: Equivalent cost-of-sales cut alone | C22: =C19/Benchmark!B6 -> 0.019781809
A23: Equivalent revenue increase alone (at the average profit margin on new sales) | C23: =C19/(Benchmark!B12/Benchmark!B5) -> 297220
A25: Takeaway: with margins this thin, small cost improvements move profit a lot, which is why labour scheduling, waste and overhead control matter more than chasing sales.

Sheet Wages
A1: Average hourly wage, accommodation and food services
A2: Source: Statistics Canada Table 14-10-0206-01 (SEPH), as published by ISED Canadian Industry Statistics, NAICS 72.
A4: Year | B4: Average hourly wage ($) | C4: Change vs prior year | D4: Cumulative change since 2020
A5: 2020 | B5: 16.78 | D5: =B5/$B$5-1 -> 0
A6: 2021 | B6: 17.1 | C6: =B6/B5-1 -> 0.019070322 | D6: =B6/$B$5-1 -> 0.019070322
A7: 2022 | B7: 18.03 | C7: =B7/B6-1 -> 0.054385965 | D7: =B7/$B$5-1 -> 0.074493445
A8: 2023 | B8: 18.62 | C8: =B8/B7-1 -> 0.032723239 | D8: =B8/$B$5-1 -> 0.10965435
A9: 2024 | B9: 19.48 | C9: =B9/B8-1 -> 0.046186896 | D9: =B9/$B$5-1 -> 0.16090584

Sheet Sources
A1: Sources
A3: Used for | B3: Source | C3: Link
A4: Average restaurant financials | B4: ISED, Canadian Industry Statistics, NAICS 7225, financial performance, 2024 (Statistics Canada data) | C4: https://ised-isde.canada.ca/app/ixb/cis/performance/rev/7225
A5: Industry-wide margin and cost structure | B5: Statistics Canada, The Daily, Food services and drinking places, annual, 2024 | C5: https://www150.statcan.gc.ca/n1/daily-quotidien/260309/dq260309a-eng.htm
A6: Hourly wage series | B6: ISED, Canadian Industry Statistics, Accommodation and food services (72), salaries and wages (Statistics Canada Table 14-10-0206-01) | C6: https://ised-isde.canada.ca/app/ixb/cis/salaries-salaires/72
A7: 2019 to 2023 annual figures | B7: Statistics Canada, The Daily, annual 2020 / 2021 / 2022 (sales surpass pre-pandemic) / 2023 releases | C7: https://www150.statcan.gc.ca/n1/daily-quotidien/220412/dq220412e-eng.htm
A8: 2021 annual | B8: Statistics Canada, The Daily, Food services and drinking places, annual, 2021 | C8: https://www150.statcan.gc.ca/n1/daily-quotidien/230216/dq230216c-eng.htm
A9: 2022 annual | B9: Statistics Canada, Sales at full-service restaurants and limited-service eating places surpass pre-pandemic levels in 2022 | C9: https://www.statcan.gc.ca/o1/en/plus/5832-sales-full-service-restaurants-and-limited-service-eating-places-surpass-pre-pandemic
A10: 2023 annual | B10: Statistics Canada, The Daily, food services and drinking places, 2023 financial data | C10: https://www150.statcan.gc.ca/n1/daily-quotidien/250218/dq250218d-eng.htm
A11: Workforce and job vacancies | B11: Statistics Canada, Workforce insights: food services and drinking places, 2017 to 2023 | C11: https://www150.statcan.gc.ca/n1/pub/11-621-m/11-621-m2025013-eng.htm
